example.cp311-win_amd64.pyd
example_sulthan4-0.0.9.dist-info/METADATA
example_sulthan4-0.0.9.dist-info/WHEEL
example_sulthan4-0.0.9.dist-info/top_level.txt
example_sulthan4-0.0.9.dist-info/RECORD
