Metadata-Version: 2.1
Name: example-sulthan4
Version: 0.0.9
Summary: Example project using pybind11
Author: Sulthan
Author-email: sulthan4380@example.com
